morse_for_python-1.0.dist-info/DESCRIPTION.rst
morse_for_python-1.0.dist-info/METADATA
morse_for_python-1.0.dist-info/RECORD
morse_for_python-1.0.dist-info/WHEEL
morse_for_python-1.0.dist-info/metadata.json
morse_for_python-1.0.dist-info/top_level.txt
pmorse/Pmorse.py
pmorse/__init__.py
