Metadata-Version: 2.0
Name: morse-for-python
Version: 1.0
Summary: morse for python
Home-page: https://github.com/sunder3344
Author: derek sunder
Author-email: sunder3344@sina.com
License: BSD License
Keywords: morse for python
Platform: UNKNOWN
Classifier: Development Status :: 4 - Beta
Classifier: Operating System :: OS Independent
Classifier: Intended Audience :: Developers
Classifier: License :: OSI Approved :: BSD License
Classifier: Programming Language :: Python
Classifier: Programming Language :: Python :: Implementation
Classifier: Programming Language :: Python :: 3
Classifier: Programming Language :: Python :: 3.4
Classifier: Programming Language :: Python :: 3.5
Classifier: Programming Language :: Python :: 3.6
Classifier: Topic :: Software Development :: Libraries
